LICENSE
frameup/__init__.py
frameup/frameup.py
frameup/serve.py
frameup/templates/example.html
frameup/templates/example.j2.html
frameup-0.1.2.dist-info/entry_points.txt
frameup-0.1.2.dist-info/LICENSE
frameup-0.1.2.dist-info/WHEEL
frameup-0.1.2.dist-info/METADATA
frameup-0.1.2.dist-info/RECORD
