Metadata-Version: 2.1
Name: frameup
Version: 0.1.2
Summary: DataFrames all up in your web applications
Home-page: https://github.com/scott2b/DataFrameup
Keywords: Pandas,DataFrame,web applications
Author: Scott Bradley
Author-email: scott@codeslick.com
Requires-Python: >=3.7,<4.0
Classifier: Development Status :: 3 - Alpha
Classifier: Intended Audience :: Developers
Classifier: License :: OSI Approved :: MIT License
Classifier: Programming Language :: Python
Classifier: Programming Language :: Python :: 3
Classifier: Programming Language :: Python :: 3.7
Classifier: Topic :: Software Development :: Libraries
Classifier: Topic :: Software Development :: Libraries :: Python Modules
Requires-Dist: pandas (>=0.23.0,<0.24.0)
Project-URL: Repository, https://github.com/scott2b/DataFrameup
